<annotation>
	<folder>jpg</folder>
	<filename>29.jpg</filename>
	<path>/Users/marina/Desktop/NewDatasetRT/jpg/29.jpg</path>
	<source>
		<database>Unknown</database>
	</source>
	<size>
		<width>720</width>
		<height>720</height>
		<depth>3</depth>
	</size>
	<segmented>0</segmented>
	<object>
		<name>Orange star</name>
		<pose>Unspecified</pose>
		<truncated>0</truncated>
		<difficult>0</difficult>
		<bndbox>
			<xmin>563</xmin>
			<ymin>26</ymin>
			<xmax>705</xmax>
			<ymax>164</ymax>
		</bndbox>
	</object>
	<object>
		<name>Green star</name>
		<pose>Unspecified</pose>
		<truncated>0</truncated>
		<difficult>0</difficult>
		<bndbox>
			<xmin>37</xmin>
			<ymin>550</ymin>
			<xmax>182</xmax>
			<ymax>693</ymax>
		</bndbox>
	</object>
	<object>
		<name>Orange square</name>
		<pose>Unspecified</pose>
		<truncated>0</truncated>
		<difficult>0</difficult>
		<bndbox>
			<xmin>569</xmin>
			<ymin>542</ymin>
			<xmax>706</xmax>
			<ymax>681</ymax>
		</bndbox>
	</object>
</annotation>
